nonebot_plugin_mc_watcher/__init__.py
nonebot_plugin_mc_watcher/config.py
nonebot_plugin_mc_watcher/globals.py
nonebot_plugin_mc_watcher/minecraft.py
nonebot_plugin_mc_watcher/timer.py
nonebot_plugin_mc_watcher-1.0.6.dist-info/LICENSE
nonebot_plugin_mc_watcher-1.0.6.dist-info/METADATA
nonebot_plugin_mc_watcher-1.0.6.dist-info/WHEEL
nonebot_plugin_mc_watcher-1.0.6.dist-info/RECORD
