Metadata-Version: 2.3
Name: nonebot_plugin_mc_watcher
Version: 1.0.6
Summary: 一个适用于监控多服务器的 Motd 工具。
License: GPL3
Keywords: nonebot,nonebot2,mc,minecraft,onebot
Author: Lonely-Sails
Requires-Python: >=3.8,<4.0
Classifier: License :: Other/Proprietary License
Classifier: Programming Language :: Python :: 3
Classifier: Programming Language :: Python :: 3.8
Classifier: Programming Language :: Python :: 3.9
Classifier: Programming Language :: Python :: 3.10
Classifier: Programming Language :: Python :: 3.11
Classifier: Programming Language :: Python :: 3.12
Classifier: Programming Language :: Python :: 3.13
Requires-Dist: mcproto (>=0.5.0,<0.6.0)
Requires-Dist: nonebot-adapter-onebot (>=2.4.3,<3.0.0)
Requires-Dist: nonebot-plugin-localstore (>=0.7.0,<0.8.0)
Requires-Dist: nonebot2 (>=2.2.0,<3.0.0)
Requires-Dist: pydantic (>=2.7.4,<3.0.0)
Project-URL: Documentation, https://github.com/Lonely-Sails/nonebot-plugin-mc-watcher#readme
Project-URL: Homepage, https://github.com/Lonely-Sails/nonebot-plugin-mc-watcher
Project-URL: Repository, https://github.com/Lonely-Sails/nonebot-plugin-mc-watcher
